fmri_toolkit/__init__.py
fmri_toolkit/simulate.py
fmri_toolkit/core/__init__.py
fmri_toolkit/core/post_hoc.py
fmri_toolkit/core/stimulus_detect.py
fmri_toolkit/core/stimulus_helper.py
fmri_toolkit/roi/__init__.py
fmri_toolkit/roi/phase1.py
fmri_toolkit/roi/phase2.py
fmri_toolkit/timeseries/__init__.py
fmri_toolkit/timeseries/analysis.py
fmri_toolkit/timeseries/forecast.py
fmri_toolkit/utils/__init__.py
fmri_toolkit/utils/image.py
fmri_toolkit/utils/load.py
fmri_toolkit/utils/p_value_adjustment.py
fmri_toolkit/utils/utils.py
fmri_toolkit/visualization/__init__.py
fmri_toolkit/visualization/comparison_2d.py
fmri_toolkit/visualization/comparison_3d.py
fmri_toolkit/visualization/comparison_internal.py
fmri_toolkit/visualization/visual_2d.py
fmri_toolkit/visualization/visual_3d.py
fmri_toolkit/visualization/visual_3d_region.py
fmri_toolkit-0.1.0.dist-info/licenses/LICENSE
fmri_toolkit-0.1.0.dist-info/METADATA
fmri_toolkit-0.1.0.dist-info/WHEEL
fmri_toolkit-0.1.0.dist-info/top_level.txt
fmri_toolkit-0.1.0.dist-info/RECORD
