Metadata-Version: 2.4
Name: fmri-toolkit
Version: 0.1.0
Summary: A comprehensive toolkit for fMRI data analysis and visualization
Author-email: Johnny In <johnnyin@umich.edu>
License: MIT
Keywords: fmri,neuroimaging,brain,neuroscience,analysis,visualization,mri
Classifier: Development Status :: 3 - Alpha
Classifier: Intended Audience :: Science/Research
Classifier: Topic :: Scientific/Engineering :: Medical Science Apps.
Classifier: Topic :: Scientific/Engineering :: Visualization
Classifier: License :: OSI Approved :: MIT License
Classifier: Programming Language :: Python :: 3
Classifier: Programming Language :: Python :: 3.8
Classifier: Programming Language :: Python :: 3.9
Classifier: Programming Language :: Python :: 3.10
Classifier: Programming Language :: Python :: 3.11
Classifier: Programming Language :: Python :: 3.12
Requires-Python: >=3.8
License-File: LICENSE
Requires-Dist: numpy>=1.20.0
Requires-Dist: scipy>=1.7.0
Requires-Dist: pandas>=1.3.0
Requires-Dist: matplotlib>=3.4.0
Requires-Dist: seaborn>=0.11.0
Requires-Dist: plotly>=5.0.0
Requires-Dist: scikit-learn>=1.0.0
Requires-Dist: statsmodels>=0.13.0
Requires-Dist: nibabel>=3.2.0
Requires-Dist: Pillow>=8.0.0
Requires-Dist: tqdm>=4.60.0
Requires-Dist: pyreadr>=0.4.0
Requires-Dist: hotelling>=0.5.0
Requires-Dist: tenacity>=8.0.0
Requires-Dist: requests>=2.25.0
Requires-Dist: plotnine>=0.8.0
Requires-Dist: python-dateutil>=2.8.0
Provides-Extra: dev
Requires-Dist: pytest>=7.0.0; extra == "dev"
Requires-Dist: pytest-cov>=3.0.0; extra == "dev"
Requires-Dist: black>=22.0.0; extra == "dev"
Requires-Dist: flake8>=4.0.0; extra == "dev"
Requires-Dist: mypy>=0.950; extra == "dev"
Dynamic: license-file
